[
  {
    "openTime": 1548656580000,
    "open": "0.00035010",
    "high": "0.00035010",
    "low": "0.00035010",
    "close": "0.00035010",
    "volume": "0.00035010",
    "closeTime": 1548656639999,
    "trades": 0
  },
  {
    "openTime": 1548656640000,
    "open": "0.00035030",
    "high": "0.00035030",
    "low": "0.00035030",
    "close": "0.00035030",
    "volume": "0.00035030",
    "closeTime": 1548656699999,
    "trades": 2
  },
  {
    "openTime": 1548656700000,
    "open": "0.00035030",
    "high": "0.00035030",
    "low": "0.00035030",
    "close": "0.00035030",
    "volume": "0.00035030",
    "closeTime": 1548656759999,
    "trades": 0
  },
  {
    "openTime": 1548656760000,
    "open": "0.00035020",
    "high": "0.00035020",
    "low": "0.00035020",
    "close": "0.00035020",
    "volume": "0.00035020",
    "closeTime": 1548656819999,
    "trades": 1
  },
  {
    "openTime": 1548656820000,
    "open": "0.00035010",
    "high": "0.00035020",
    "low": "0.00035010",
    "close": "0.00035010",
    "volume": "0.00035010",
    "closeTime": 1548656879999,
    "trades": 5
  },
  {
    "openTime": 1548656880000,
    "open": "0.00035010",
    "high": "0.00035010",
    "low": "0.00035010",
    "close": "0.00035010",
    "volume": "0.00035010",
    "closeTime": 1548656939999,
    "trades": 1
  },
  {
    "openTime": 1548656940000,
    "open": "0.00035010",
    "high": "0.00035010",
    "low": "0.00035010",
    "close": "0.00035010",
    "volume": "0.00035010",
    "closeTime": 1548656999999,
    "trades": 0
  },
  {
    "openTime": 1548657000000,
    "open": "0.00035020",
    "high": "0.00035020",
    "low": "0.00035020",
    "close": "0.00035020",
    "volume": "0.00035020",
    "closeTime": 1548657059999,
    "trades": 2
  },
  {
    "openTime": 1548657060000,
    "open": "0.00035030",
    "high": "0.00035030",
    "low": "0.00035030",
    "close": "0.00035030",
    "volume": "0.00035030",
    "closeTime": 1548657119999,
    "trades": 3
  },
  {
    "openTime": 1548657120000,
    "open": "0.00035030",
    "high": "0.00035190",
    "low": "0.00035030",
    "close": "0.00035190",
    "volume": "0.00035030",
    "closeTime": 1548657179999,
    "trades": 9
  },
  {
    "openTime": 1548657180000,
    "open": "0.00035170",
    "high": "0.00035190",
    "low": "0.00035170",
    "close": "0.00035190",
    "volume": "0.00035170",
    "closeTime": 1548657239999,
    "trades": 2
  },
  {
    "openTime": 1548657240000,
    "open": "0.00035190",
    "high": "0.00035190",
    "low": "0.00035190",
    "close": "0.00035190",
    "volume": "0.00035190",
    "closeTime": 1548657299999,
    "trades": 0
  },
  {
    "openTime": 1548657300000,
    "open": "0.00035190",
    "high": "0.00035190",
    "low": "0.00035190",
    "close": "0.00035190",
    "volume": "0.00035190",
    "closeTime": 1548657359999,
    "trades": 0
  },
  {
    "openTime": 1548657360000,
    "open": "0.00035190",
    "high": "0.00035190",
    "low": "0.00035190",
    "close": "0.00035190",
    "volume": "0.00035190",
    "closeTime": 1548657419999,
    "trades": 0
  },
  {
    "openTime": 1548657420000,
    "open": "0.00035190",
    "high": "0.00035190",
    "low": "0.00035190",
    "close": "0.00035190",
    "volume": "0.00035190",
    "closeTime": 1548657479999,
    "trades": 0
  },
  {
    "openTime": 1548657480000,
    "open": "0.00035270",
    "high": "0.00035320",
    "low": "0.00035270",
    "close": "0.00035320",
    "volume": "0.00035270",
    "closeTime": 1548657539999,
    "trades": 15
  },
  {
    "openTime": 1548657540000,
    "open": "0.00035320",
    "high": "0.00035320",
    "low": "0.00035320",
    "close": "0.00035320",
    "volume": "0.00035320",
    "closeTime": 1548657599999,
    "trades": 0
  },
  {
    "openTime": 1548657600000,
    "open": "0.00035300",
    "high": "0.00035320",
    "low": "0.00035300",
    "close": "0.00035320",
    "volume": "0.00035300",
    "closeTime": 1548657659999,
    "trades": 11
  },
  {
    "openTime": 1548657660000,
    "open": "0.00035320",
    "high": "0.00035320",
    "low": "0.00035300",
    "close": "0.00035320",
    "volume": "0.00035320",
    "closeTime": 1548657719999,
    "trades": 4
  },
  {
    "openTime": 1548657720000,
    "open": "0.00035320",
    "high": "0.00035360",
    "low": "0.00035300",
    "close": "0.00035360",
    "volume": "0.00035320",
    "closeTime": 1548657779999,
    "trades": 22
  },
  {
    "openTime": 1548657780000,
    "open": "0.00035400",
    "high": "0.00035470",
    "low": "0.00035400",
    "close": "0.00035470",
    "volume": "0.00035400",
    "closeTime": 1548657839999,
    "trades": 15
  },
  {
    "openTime": 1548657840000,
    "open": "0.00035400",
    "high": "0.00035400",
    "low": "0.00035400",
    "close": "0.00035400",
    "volume": "0.00035400",
    "closeTime": 1548657899999,
    "trades": 1
  },
  {
    "openTime": 1548657900000,
    "open": "0.00035470",
    "high": "0.00035480",
    "low": "0.00035450",
    "close": "0.00035450",
    "volume": "0.00035470",
    "closeTime": 1548657959999,
    "trades": 6
  },
  {
    "openTime": 1548657960000,
    "open": "0.00035450",
    "high": "0.00035450",
    "low": "0.00035450",
    "close": "0.00035450",
    "volume": "0.00035450",
    "closeTime": 1548658019999,
    "trades": 0
  },
  {
    "openTime": 1548658020000,
    "open": "0.00035400",
    "high": "0.00035440",
    "low": "0.00035220",
    "close": "0.00035440",
    "volume": "0.00035400",
    "closeTime": 1548658079999,
    "trades": 10
  },
  {
    "openTime": 1548658080000,
    "open": "0.00035270",
    "high": "0.00035270",
    "low": "0.00035260",
    "close": "0.00035260",
    "volume": "0.00035270",
    "closeTime": 1548658139999,
    "trades": 5
  },
  {
    "openTime": 1548658140000,
    "open": "0.00035260",
    "high": "0.00035260",
    "low": "0.00035260",
    "close": "0.00035260",
    "volume": "0.00035260",
    "closeTime": 1548658199999,
    "trades": 0
  },
  {
    "openTime": 1548658200000,
    "open": "0.00035260",
    "high": "0.00035260",
    "low": "0.00035260",
    "close": "0.00035260",
    "volume": "0.00035260",
    "closeTime": 1548658259999,
    "trades": 0
  },
  {
    "openTime": 1548658260000,
    "open": "0.00035240",
    "high": "0.00035270",
    "low": "0.00035240",
    "close": "0.00035270",
    "volume": "0.00035240",
    "closeTime": 1548658319999,
    "trades": 2
  },
  {
    "openTime": 1548658320000,
    "open": "0.00035270",
    "high": "0.00035270",
    "low": "0.00035220",
    "close": "0.00035220",
    "volume": "0.00035270",
    "closeTime": 1548658379999,
    "trades": 3
  },
  {
    "openTime": 1548658380000,
    "open": "0.00035220",
    "high": "0.00035220",
    "low": "0.00035220",
    "close": "0.00035220",
    "volume": "0.00035220",
    "closeTime": 1548658439999,
    "trades": 0
  },
  {
    "openTime": 1548658440000,
    "open": "0.00035230",
    "high": "0.00035230",
    "low": "0.00035220",
    "close": "0.00035220",
    "volume": "0.00035230",
    "closeTime": 1548658499999,
    "trades": 2
  },
  {
    "openTime": 1548658500000,
    "open": "0.00035220",
    "high": "0.00035370",
    "low": "0.00035200",
    "close": "0.00035370",
    "volume": "0.00035220",
    "closeTime": 1548658559999,
    "trades": 6
  },
  {
    "openTime": 1548658560000,
    "open": "0.00035370",
    "high": "0.00035370",
    "low": "0.00035370",
    "close": "0.00035370",
    "volume": "0.00035370",
    "closeTime": 1548658619999,
    "trades": 0
  },
  {
    "openTime": 1548658620000,
    "open": "0.00035370",
    "high": "0.00035370",
    "low": "0.00035370",
    "close": "0.00035370",
    "volume": "0.00035370",
    "closeTime": 1548658679999,
    "trades": 0
  },
  {
    "openTime": 1548658680000,
    "open": "0.00035370",
    "high": "0.00035370",
    "low": "0.00035370",
    "close": "0.00035370",
    "volume": "0.00035370",
    "closeTime": 1548658739999,
    "trades": 0
  },
  {
    "openTime": 1548658740000,
    "open": "0.00035370",
    "high": "0.00035370",
    "low": "0.00035370",
    "close": "0.00035370",
    "volume": "0.00035370",
    "closeTime": 1548658799999,
    "trades": 0
  },
  {
    "openTime": 1548658800000,
    "open": "0.00035370",
    "high": "0.00035370",
    "low": "0.00035370",
    "close": "0.00035370",
    "volume": "0.00035370",
    "closeTime": 1548658859999,
    "trades": 0
  },
  {
    "openTime": 1548658860000,
    "open": "0.00035370",
    "high": "0.00035370",
    "low": "0.00035370",
    "close": "0.00035370",
    "volume": "0.00035370",
    "closeTime": 1548658919999,
    "trades": 0
  },
  {
    "openTime": 1548658920000,
    "open": "0.00035370",
    "high": "0.00035370",
    "low": "0.00035370",
    "close": "0.00035370",
    "volume": "0.00035370",
    "closeTime": 1548658979999,
    "trades": 2
  },
  {
    "openTime": 1548658980000,
    "open": "0.00035200",
    "high": "0.00035200",
    "low": "0.00035190",
    "close": "0.00035190",
    "volume": "0.00035200",
    "closeTime": 1548659039999,
    "trades": 3
  },
  {
    "openTime": 1548659040000,
    "open": "0.00035190",
    "high": "0.00035190",
    "low": "0.00035190",
    "close": "0.00035190",
    "volume": "0.00035190",
    "closeTime": 1548659099999,
    "trades": 0
  },
  {
    "openTime": 1548659100000,
    "open": "0.00035190",
    "high": "0.00035190",
    "low": "0.00035190",
    "close": "0.00035190",
    "volume": "0.00035190",
    "closeTime": 1548659159999,
    "trades": 0
  },
  {
    "openTime": 1548659160000,
    "open": "0.00035190",
    "high": "0.00035190",
    "low": "0.00035190",
    "close": "0.00035190",
    "volume": "0.00035190",
    "closeTime": 1548659219999,
    "trades": 0
  },
  {
    "openTime": 1548659220000,
    "open": "0.00035190",
    "high": "0.00035190",
    "low": "0.00035190",
    "close": "0.00035190",
    "volume": "0.00035190",
    "closeTime": 1548659279999,
    "trades": 0
  },
  {
    "openTime": 1548659280000,
    "open": "0.00035190",
    "high": "0.00035190",
    "low": "0.00035190",
    "close": "0.00035190",
    "volume": "0.00035190",
    "closeTime": 1548659339999,
    "trades": 0
  },
  {
    "openTime": 1548659340000,
    "open": "0.00035190",
    "high": "0.00035190",
    "low": "0.00035190",
    "close": "0.00035190",
    "volume": "0.00035190",
    "closeTime": 1548659399999,
    "trades": 0
  },
  {
    "openTime": 1548659400000,
    "open": "0.00035190",
    "high": "0.00035190",
    "low": "0.00035190",
    "close": "0.00035190",
    "volume": "0.00035190",
    "closeTime": 1548659459999,
    "trades": 0
  },
  {
    "openTime": 1548659460000,
    "open": "0.00035200",
    "high": "0.00035260",
    "low": "0.00035070",
    "close": "0.00035260",
    "volume": "0.00035200",
    "closeTime": 1548659519999,
    "trades": 8
  },
  {
    "openTime": 1548659520000,
    "open": "0.00035260",
    "high": "0.00035260",
    "low": "0.00035260",
    "close": "0.00035260",
    "volume": "0.00035260",
    "closeTime": 1548659579999,
    "trades": 1
  },
  {
    "openTime": 1548659580000,
    "open": "0.00035260",
    "high": "0.00035260",
    "low": "0.00035260",
    "close": "0.00035260",
    "volume": "0.00035260",
    "closeTime": 1548659639999,
    "trades": 0
  },
  {
    "openTime": 1548659640000,
    "open": "0.00035260",
    "high": "0.00035260",
    "low": "0.00035260",
    "close": "0.00035260",
    "volume": "0.00035260",
    "closeTime": 1548659699999,
    "trades": 0
  },
  {
    "openTime": 1548659700000,
    "open": "0.00035260",
    "high": "0.00035260",
    "low": "0.00035260",
    "close": "0.00035260",
    "volume": "0.00035260",
    "closeTime": 1548659759999,
    "trades": 0
  },
  {
    "openTime": 1548659760000,
    "open": "0.00035210",
    "high": "0.00035210",
    "low": "0.00035210",
    "close": "0.00035210",
    "volume": "0.00035210",
    "closeTime": 1548659819999,
    "trades": 1
  },
  {
    "openTime": 1548659820000,
    "open": "0.00035210",
    "high": "0.00035210",
    "low": "0.00035210",
    "close": "0.00035210",
    "volume": "0.00035210",
    "closeTime": 1548659879999,
    "trades": 1
  },
  {
    "openTime": 1548659880000,
    "open": "0.00035210",
    "high": "0.00035210",
    "low": "0.00035210",
    "close": "0.00035210",
    "volume": "0.00035210",
    "closeTime": 1548659939999,
    "trades": 0
  },
  {
    "openTime": 1548659940000,
    "open": "0.00035210",
    "high": "0.00035210",
    "low": "0.00035210",
    "close": "0.00035210",
    "volume": "0.00035210",
    "closeTime": 1548659999999,
    "trades": 0
  },
  {
    "openTime": 1548660000000,
    "open": "0.00035140",
    "high": "0.00035140",
    "low": "0.00035140",
    "close": "0.00035140",
    "volume": "0.00035140",
    "closeTime": 1548660059999,
    "trades": 1
  },
  {
    "openTime": 1548660060000,
    "open": "0.00035140",
    "high": "0.00035140",
    "low": "0.00035140",
    "close": "0.00035140",
    "volume": "0.00035140",
    "closeTime": 1548660119999,
    "trades": 0
  },
  {
    "openTime": 1548660120000,
    "open": "0.00035120",
    "high": "0.00035200",
    "low": "0.00035120",
    "close": "0.00035200",
    "volume": "0.00035120",
    "closeTime": 1548660179999,
    "trades": 3
  },
  {
    "openTime": 1548660180000,
    "open": "0.00035200",
    "high": "0.00035200",
    "low": "0.00034980",
    "close": "0.00035030",
    "volume": "0.00035200",
    "closeTime": 1548660239999,
    "trades": 41
  },
  {
    "openTime": 1548660240000,
    "open": "0.00035130",
    "high": "0.00035150",
    "low": "0.00035130",
    "close": "0.00035150",
    "volume": "0.00035130",
    "closeTime": 1548660299999,
    "trades": 2
  },
  {
    "openTime": 1548660300000,
    "open": "0.00035070",
    "high": "0.00035070",
    "low": "0.00034990",
    "close": "0.00034990",
    "volume": "0.00035070",
    "closeTime": 1548660359999,
    "trades": 2
  },
  {
    "openTime": 1548660360000,
    "open": "0.00035110",
    "high": "0.00035110",
    "low": "0.00035110",
    "close": "0.00035110",
    "volume": "0.00035110",
    "closeTime": 1548660419999,
    "trades": 1
  },
  {
    "openTime": 1548660420000,
    "open": "0.00035110",
    "high": "0.00035110",
    "low": "0.00035110",
    "close": "0.00035110",
    "volume": "0.00035110",
    "closeTime": 1548660479999,
    "trades": 0
  },
  {
    "openTime": 1548660480000,
    "open": "0.00035140",
    "high": "0.00035140",
    "low": "0.00034980",
    "close": "0.00034980",
    "volume": "0.00035140",
    "closeTime": 1548660539999,
    "trades": 5
  },
  {
    "openTime": 1548660540000,
    "open": "0.00035130",
    "high": "0.00035130",
    "low": "0.00035130",
    "close": "0.00035130",
    "volume": "0.00035130",
    "closeTime": 1548660599999,
    "trades": 1
  },
  {
    "openTime": 1548660600000,
    "open": "0.00035130",
    "high": "0.00035130",
    "low": "0.00035130",
    "close": "0.00035130",
    "volume": "0.00035130",
    "closeTime": 1548660659999,
    "trades": 0
  },
  {
    "openTime": 1548660660000,
    "open": "0.00035130",
    "high": "0.00035130",
    "low": "0.00035130",
    "close": "0.00035130",
    "volume": "0.00035130",
    "closeTime": 1548660719999,
    "trades": 0
  },
  {
    "openTime": 1548660720000,
    "open": "0.00035150",
    "high": "0.00035150",
    "low": "0.00035150",
    "close": "0.00035150",
    "volume": "0.00035150",
    "closeTime": 1548660779999,
    "trades": 1
  },
  {
    "openTime": 1548660780000,
    "open": "0.00035150",
    "high": "0.00035150",
    "low": "0.00035150",
    "close": "0.00035150",
    "volume": "0.00035150",
    "closeTime": 1548660839999,
    "trades": 2
  },
  {
    "openTime": 1548660840000,
    "open": "0.00035150",
    "high": "0.00035150",
    "low": "0.00035150",
    "close": "0.00035150",
    "volume": "0.00035150",
    "closeTime": 1548660899999,
    "trades": 0
  },
  {
    "openTime": 1548660900000,
    "open": "0.00035150",
    "high": "0.00035150",
    "low": "0.00035150",
    "close": "0.00035150",
    "volume": "0.00035150",
    "closeTime": 1548660959999,
    "trades": 0
  },
  {
    "openTime": 1548660960000,
    "open": "0.00035150",
    "high": "0.00035150",
    "low": "0.00035150",
    "close": "0.00035150",
    "volume": "0.00035150",
    "closeTime": 1548661019999,
    "trades": 0
  },
  {
    "openTime": 1548661020000,
    "open": "0.00035150",
    "high": "0.00035150",
    "low": "0.00035150",
    "close": "0.00035150",
    "volume": "0.00035150",
    "closeTime": 1548661079999,
    "trades": 0
  },
  {
    "openTime": 1548661080000,
    "open": "0.00035150",
    "high": "0.00035150",
    "low": "0.00035150",
    "close": "0.00035150",
    "volume": "0.00035150",
    "closeTime": 1548661139999,
    "trades": 0
  },
  {
    "openTime": 1548661140000,
    "open": "0.00035150",
    "high": "0.00035150",
    "low": "0.00035150",
    "close": "0.00035150",
    "volume": "0.00035150",
    "closeTime": 1548661199999,
    "trades": 0
  },
  {
    "openTime": 1548661200000,
    "open": "0.00035150",
    "high": "0.00035150",
    "low": "0.00035150",
    "close": "0.00035150",
    "volume": "0.00035150",
    "closeTime": 1548661259999,
    "trades": 0
  },
  {
    "openTime": 1548661260000,
    "open": "0.00035150",
    "high": "0.00035150",
    "low": "0.00035150",
    "close": "0.00035150",
    "volume": "0.00035150",
    "closeTime": 1548661319999,
    "trades": 0
  },
  {
    "openTime": 1548661320000,
    "open": "0.00035150",
    "high": "0.00035150",
    "low": "0.00035150",
    "close": "0.00035150",
    "volume": "0.00035150",
    "closeTime": 1548661379999,
    "trades": 0
  },
  {
    "openTime": 1548661380000,
    "open": "0.00035020",
    "high": "0.00035050",
    "low": "0.00035020",
    "close": "0.00035050",
    "volume": "0.00035020",
    "closeTime": 1548661439999,
    "trades": 2
  },
  {
    "openTime": 1548661440000,
    "open": "0.00035050",
    "high": "0.00035050",
    "low": "0.00035050",
    "close": "0.00035050",
    "volume": "0.00035050",
    "closeTime": 1548661499999,
    "trades": 0
  },
  {
    "openTime": 1548661500000,
    "open": "0.00035020",
    "high": "0.00035020",
    "low": "0.00035020",
    "close": "0.00035020",
    "volume": "0.00035020",
    "closeTime": 1548661559999,
    "trades": 1
  },
  {
    "openTime": 1548661560000,
    "open": "0.00035020",
    "high": "0.00035020",
    "low": "0.00035020",
    "close": "0.00035020",
    "volume": "0.00035020",
    "closeTime": 1548661619999,
    "trades": 0
  },
  {
    "openTime": 1548661620000,
    "open": "0.00035050",
    "high": "0.00035050",
    "low": "0.00035050",
    "close": "0.00035050",
    "volume": "0.00035050",
    "closeTime": 1548661679999,
    "trades": 1
  },
  {
    "openTime": 1548661680000,
    "open": "0.00035050",
    "high": "0.00035120",
    "low": "0.00035050",
    "close": "0.00035120",
    "volume": "0.00035050",
    "closeTime": 1548661739999,
    "trades": 4
  },
  {
    "openTime": 1548661740000,
    "open": "0.00035120",
    "high": "0.00035120",
    "low": "0.00035120",
    "close": "0.00035120",
    "volume": "0.00035120",
    "closeTime": 1548661799999,
    "trades": 0
  },
  {
    "openTime": 1548661800000,
    "open": "0.00035140",
    "high": "0.00035140",
    "low": "0.00035140",
    "close": "0.00035140",
    "volume": "0.00035140",
    "closeTime": 1548661859999,
    "trades": 1
  },
  {
    "openTime": 1548661860000,
    "open": "0.00035140",
    "high": "0.00035140",
    "low": "0.00035140",
    "close": "0.00035140",
    "volume": "0.00035140",
    "closeTime": 1548661919999,
    "trades": 0
  },
  {
    "openTime": 1548661920000,
    "open": "0.00035140",
    "high": "0.00035140",
    "low": "0.00035140",
    "close": "0.00035140",
    "volume": "0.00035140",
    "closeTime": 1548661979999,
    "trades": 0
  },
  {
    "openTime": 1548661980000,
    "open": "0.00035140",
    "high": "0.00035140",
    "low": "0.00035140",
    "close": "0.00035140",
    "volume": "0.00035140",
    "closeTime": 1548662039999,
    "trades": 0
  },
  {
    "openTime": 1548662040000,
    "open": "0.00035140",
    "high": "0.00035140",
    "low": "0.00035140",
    "close": "0.00035140",
    "volume": "0.00035140",
    "closeTime": 1548662099999,
    "trades": 0
  },
  {
    "openTime": 1548662100000,
    "open": "0.00035140",
    "high": "0.00035140",
    "low": "0.00035140",
    "close": "0.00035140",
    "volume": "0.00035140",
    "closeTime": 1548662159999,
    "trades": 0
  },
  {
    "openTime": 1548662160000,
    "open": "0.00035140",
    "high": "0.00035140",
    "low": "0.00035140",
    "close": "0.00035140",
    "volume": "0.00035140",
    "closeTime": 1548662219999,
    "trades": 0
  },
  {
    "openTime": 1548662220000,
    "open": "0.00035050",
    "high": "0.00035050",
    "low": "0.00035010",
    "close": "0.00035010",
    "volume": "0.00035050",
    "closeTime": 1548662279999,
    "trades": 4
  },
  {
    "openTime": 1548662280000,
    "open": "0.00035010",
    "high": "0.00035010",
    "low": "0.00035010",
    "close": "0.00035010",
    "volume": "0.00035010",
    "closeTime": 1548662339999,
    "trades": 0
  },
  {
    "openTime": 1548662340000,
    "open": "0.00035010",
    "high": "0.00035010",
    "low": "0.00035010",
    "close": "0.00035010",
    "volume": "0.00035010",
    "closeTime": 1548662399999,
    "trades": 0
  },
  {
    "openTime": 1548662400000,
    "open": "0.00035020",
    "high": "0.00035020",
    "low": "0.00035020",
    "close": "0.00035020",
    "volume": "0.00035020",
    "closeTime": 1548662459999,
    "trades": 3
  },
  {
    "openTime": 1548662460000,
    "open": "0.00035020",
    "high": "0.00035020",
    "low": "0.00035010",
    "close": "0.00035010",
    "volume": "0.00035020",
    "closeTime": 1548662519999,
    "trades": 2
  },
  {
    "openTime": 1548662520000,
    "open": "0.00035010",
    "high": "0.00035010",
    "low": "0.00035010",
    "close": "0.00035010",
    "volume": "0.00035010",
    "closeTime": 1548662579999,
    "trades": 0
  },
  {
    "openTime": 1548662580000,
    "open": "0.00035010",
    "high": "0.00035010",
    "low": "0.00035010",
    "close": "0.00035010",
    "volume": "0.00035010",
    "closeTime": 1548662639999,
    "trades": 1
  },
  {
    "openTime": 1548662640000,
    "open": "0.00035010",
    "high": "0.00035010",
    "low": "0.00035010",
    "close": "0.00035010",
    "volume": "0.00035010",
    "closeTime": 1548662699999,
    "trades": 0
  },
  {
    "openTime": 1548662700000,
    "open": "0.00035010",
    "high": "0.00035010",
    "low": "0.00035010",
    "close": "0.00035010",
    "volume": "0.00035010",
    "closeTime": 1548662759999,
    "trades": 0
  },
  {
    "openTime": 1548662760000,
    "open": "0.00035030",
    "high": "0.00035030",
    "low": "0.00035030",
    "close": "0.00035030",
    "volume": "0.00035030",
    "closeTime": 1548662819999,
    "trades": 1
  },
  {
    "openTime": 1548662820000,
    "open": "0.00035040",
    "high": "0.00035040",
    "low": "0.00035040",
    "close": "0.00035040",
    "volume": "0.00035040",
    "closeTime": 1548662879999,
    "trades": 1
  },
  {
    "openTime": 1548662880000,
    "open": "0.00035040",
    "high": "0.00035040",
    "low": "0.00035040",
    "close": "0.00035040",
    "volume": "0.00035040",
    "closeTime": 1548662939999,
    "trades": 0
  },
  {
    "openTime": 1548662940000,
    "open": "0.00035040",
    "high": "0.00035040",
    "low": "0.00035040",
    "close": "0.00035040",
    "volume": "0.00035040",
    "closeTime": 1548662999999,
    "trades": 0
  },
  {
    "openTime": 1548663000000,
    "open": "0.00035040",
    "high": "0.00035040",
    "low": "0.00035040",
    "close": "0.00035040",
    "volume": "0.00035040",
    "closeTime": 1548663059999,
    "trades": 0
  },
  {
    "openTime": 1548663060000,
    "open": "0.00035040",
    "high": "0.00035040",
    "low": "0.00035040",
    "close": "0.00035040",
    "volume": "0.00035040",
    "closeTime": 1548663119999,
    "trades": 0
  },
  {
    "openTime": 1548663120000,
    "open": "0.00035050",
    "high": "0.00035050",
    "low": "0.00035050",
    "close": "0.00035050",
    "volume": "0.00035050",
    "closeTime": 1548663179999,
    "trades": 1
  },
  {
    "openTime": 1548663180000,
    "open": "0.00035050",
    "high": "0.00035050",
    "low": "0.00035050",
    "close": "0.00035050",
    "volume": "0.00035050",
    "closeTime": 1548663239999,
    "trades": 0
  },
  {
    "openTime": 1548663240000,
    "open": "0.00035090",
    "high": "0.00035090",
    "low": "0.00035090",
    "close": "0.00035090",
    "volume": "0.00035090",
    "closeTime": 1548663299999,
    "trades": 1
  },
  {
    "openTime": 1548663300000,
    "open": "0.00035090",
    "high": "0.00035090",
    "low": "0.00035090",
    "close": "0.00035090",
    "volume": "0.00035090",
    "closeTime": 1548663359999,
    "trades": 0
  },
  {
    "openTime": 1548663360000,
    "open": "0.00035050",
    "high": "0.00035050",
    "low": "0.00035030",
    "close": "0.00035030",
    "volume": "0.00035050",
    "closeTime": 1548663419999,
    "trades": 6
  },
  {
    "openTime": 1548663420000,
    "open": "0.00035030",
    "high": "0.00035030",
    "low": "0.00035030",
    "close": "0.00035030",
    "volume": "0.00035030",
    "closeTime": 1548663479999,
    "trades": 0
  },
  {
    "openTime": 1548663480000,
    "open": "0.00035030",
    "high": "0.00035030",
    "low": "0.00035030",
    "close": "0.00035030",
    "volume": "0.00035030",
    "closeTime": 1548663539999,
    "trades": 0
  },
  {
    "openTime": 1548663540000,
    "open": "0.00035090",
    "high": "0.00035090",
    "low": "0.00035090",
    "close": "0.00035090",
    "volume": "0.00035090",
    "closeTime": 1548663599999,
    "trades": 2
  },
  {
    "openTime": 1548663600000,
    "open": "0.00035090",
    "high": "0.00035090",
    "low": "0.00035090",
    "close": "0.00035090",
    "volume": "0.00035090",
    "closeTime": 1548663659999,
    "trades": 0
  },
  {
    "openTime": 1548663660000,
    "open": "0.00035080",
    "high": "0.00035080",
    "low": "0.00035070",
    "close": "0.00035070",
    "volume": "0.00035080",
    "closeTime": 1548663719999,
    "trades": 3
  },
  {
    "openTime": 1548663720000,
    "open": "0.00035080",
    "high": "0.00035080",
    "low": "0.00035080",
    "close": "0.00035080",
    "volume": "0.00035080",
    "closeTime": 1548663779999,
    "trades": 3
  },
  {
    "openTime": 1548663780000,
    "open": "0.00035080",
    "high": "0.00035080",
    "low": "0.00035080",
    "close": "0.00035080",
    "volume": "0.00035080",
    "closeTime": 1548663839999,
    "trades": 1
  },
  {
    "openTime": 1548663840000,
    "open": "0.00035080",
    "high": "0.00035080",
    "low": "0.00035080",
    "close": "0.00035080",
    "volume": "0.00035080",
    "closeTime": 1548663899999,
    "trades": 1
  },
  {
    "openTime": 1548663900000,
    "open": "0.00035030",
    "high": "0.00035150",
    "low": "0.00035010",
    "close": "0.00035150",
    "volume": "0.00035030",
    "closeTime": 1548663959999,
    "trades": 14
  },
  {
    "openTime": 1548663960000,
    "open": "0.00035150",
    "high": "0.00035150",
    "low": "0.00035150",
    "close": "0.00035150",
    "volume": "0.00035150",
    "closeTime": 1548664019999,
    "trades": 0
  },
  {
    "openTime": 1548664020000,
    "open": "0.00035150",
    "high": "0.00035150",
    "low": "0.00035150",
    "close": "0.00035150",
    "volume": "0.00035150",
    "closeTime": 1548664079999,
    "trades": 0
  },
  {
    "openTime": 1548664080000,
    "open": "0.00035150",
    "high": "0.00035150",
    "low": "0.00035150",
    "close": "0.00035150",
    "volume": "0.00035150",
    "closeTime": 1548664139999,
    "trades": 0
  },
  {
    "openTime": 1548664140000,
    "open": "0.00035150",
    "high": "0.00035150",
    "low": "0.00035150",
    "close": "0.00035150",
    "volume": "0.00035150",
    "closeTime": 1548664199999,
    "trades": 0
  },
  {
    "openTime": 1548664200000,
    "open": "0.00035150",
    "high": "0.00035150",
    "low": "0.00035150",
    "close": "0.00035150",
    "volume": "0.00035150",
    "closeTime": 1548664259999,
    "trades": 1
  },
  {
    "openTime": 1548664260000,
    "open": "0.00035150",
    "high": "0.00035150",
    "low": "0.00035150",
    "close": "0.00035150",
    "volume": "0.00035150",
    "closeTime": 1548664319999,
    "trades": 0
  },
  {
    "openTime": 1548664320000,
    "open": "0.00035110",
    "high": "0.00035110",
    "low": "0.00035100",
    "close": "0.00035100",
    "volume": "0.00035110",
    "closeTime": 1548664379999,
    "trades": 2
  },
  {
    "openTime": 1548664380000,
    "open": "0.00035100",
    "high": "0.00035100",
    "low": "0.00035100",
    "close": "0.00035100",
    "volume": "0.00035100",
    "closeTime": 1548664439999,
    "trades": 0
  },
  {
    "openTime": 1548664440000,
    "open": "0.00035100",
    "high": "0.00035100",
    "low": "0.00035100",
    "close": "0.00035100",
    "volume": "0.00035100",
    "closeTime": 1548664499999,
    "trades": 0
  },
  {
    "openTime": 1548664500000,
    "open": "0.00035100",
    "high": "0.00035100",
    "low": "0.00035100",
    "close": "0.00035100",
    "volume": "0.00035100",
    "closeTime": 1548664559999,
    "trades": 0
  },
  {
    "openTime": 1548664560000,
    "open": "0.00035100",
    "high": "0.00035100",
    "low": "0.00035100",
    "close": "0.00035100",
    "volume": "0.00035100",
    "closeTime": 1548664619999,
    "trades": 0
  },
  {
    "openTime": 1548664620000,
    "open": "0.00035100",
    "high": "0.00035100",
    "low": "0.00035100",
    "close": "0.00035100",
    "volume": "0.00035100",
    "closeTime": 1548664679999,
    "trades": 0
  },
  {
    "openTime": 1548664680000,
    "open": "0.00035100",
    "high": "0.00035100",
    "low": "0.00035100",
    "close": "0.00035100",
    "volume": "0.00035100",
    "closeTime": 1548664739999,
    "trades": 0
  },
  {
    "openTime": 1548664740000,
    "open": "0.00035150",
    "high": "0.00035150",
    "low": "0.00035150",
    "close": "0.00035150",
    "volume": "0.00035150",
    "closeTime": 1548664799999,
    "trades": 1
  },
  {
    "openTime": 1548664800000,
    "open": "0.00035180",
    "high": "0.00035340",
    "low": "0.00035180",
    "close": "0.00035340",
    "volume": "0.00035180",
    "closeTime": 1548664859999,
    "trades": 2
  },
  {
    "openTime": 1548664860000,
    "open": "0.00035340",
    "high": "0.00035350",
    "low": "0.00035340",
    "close": "0.00035350",
    "volume": "0.00035340",
    "closeTime": 1548664919999,
    "trades": 2
  },
  {
    "openTime": 1548664920000,
    "open": "0.00035150",
    "high": "0.00035150",
    "low": "0.00035150",
    "close": "0.00035150",
    "volume": "0.00035150",
    "closeTime": 1548664979999,
    "trades": 2
  },
  {
    "openTime": 1548664980000,
    "open": "0.00035150",
    "high": "0.00035180",
    "low": "0.00035150",
    "close": "0.00035180",
    "volume": "0.00035150",
    "closeTime": 1548665039999,
    "trades": 3
  },
  {
    "openTime": 1548665040000,
    "open": "0.00035180",
    "high": "0.00035180",
    "low": "0.00035180",
    "close": "0.00035180",
    "volume": "0.00035180",
    "closeTime": 1548665099999,
    "trades": 0
  },
  {
    "openTime": 1548665100000,
    "open": "0.00035180",
    "high": "0.00035180",
    "low": "0.00035180",
    "close": "0.00035180",
    "volume": "0.00035180",
    "closeTime": 1548665159999,
    "trades": 0
  },
  {
    "openTime": 1548665160000,
    "open": "0.00035180",
    "high": "0.00035180",
    "low": "0.00035180",
    "close": "0.00035180",
    "volume": "0.00035180",
    "closeTime": 1548665219999,
    "trades": 0
  },
  {
    "openTime": 1548665220000,
    "open": "0.00035250",
    "high": "0.00035250",
    "low": "0.00035250",
    "close": "0.00035250",
    "volume": "0.00035250",
    "closeTime": 1548665279999,
    "trades": 1
  },
  {
    "openTime": 1548665280000,
    "open": "0.00035250",
    "high": "0.00035250",
    "low": "0.00035120",
    "close": "0.00035120",
    "volume": "0.00035250",
    "closeTime": 1548665339999,
    "trades": 3
  },
  {
    "openTime": 1548665340000,
    "open": "0.00035240",
    "high": "0.00035240",
    "low": "0.00035240",
    "close": "0.00035240",
    "volume": "0.00035240",
    "closeTime": 1548665399999,
    "trades": 1
  },
  {
    "openTime": 1548665400000,
    "open": "0.00035240",
    "high": "0.00035240",
    "low": "0.00035240",
    "close": "0.00035240",
    "volume": "0.00035240",
    "closeTime": 1548665459999,
    "trades": 0
  },
  {
    "openTime": 1548665460000,
    "open": "0.00035240",
    "high": "0.00035240",
    "low": "0.00035240",
    "close": "0.00035240",
    "volume": "0.00035240",
    "closeTime": 1548665519999,
    "trades": 0
  },
  {
    "openTime": 1548665520000,
    "open": "0.00035240",
    "high": "0.00035240",
    "low": "0.00035240",
    "close": "0.00035240",
    "volume": "0.00035240",
    "closeTime": 1548665579999,
    "trades": 0
  },
  {
    "openTime": 1548665580000,
    "open": "0.00035240",
    "high": "0.00035240",
    "low": "0.00035240",
    "close": "0.00035240",
    "volume": "0.00035240",
    "closeTime": 1548665639999,
    "trades": 0
  },
  {
    "openTime": 1548665640000,
    "open": "0.00035240",
    "high": "0.00035240",
    "low": "0.00035240",
    "close": "0.00035240",
    "volume": "0.00035240",
    "closeTime": 1548665699999,
    "trades": 0
  },
  {
    "openTime": 1548665700000,
    "open": "0.00035240",
    "high": "0.00035240",
    "low": "0.00035240",
    "close": "0.00035240",
    "volume": "0.00035240",
    "closeTime": 1548665759999,
    "trades": 0
  },
  {
    "openTime": 1548665760000,
    "open": "0.00035240",
    "high": "0.00035240",
    "low": "0.00035240",
    "close": "0.00035240",
    "volume": "0.00035240",
    "closeTime": 1548665819999,
    "trades": 0
  },
  {
    "openTime": 1548665820000,
    "open": "0.00035240",
    "high": "0.00035240",
    "low": "0.00035240",
    "close": "0.00035240",
    "volume": "0.00035240",
    "closeTime": 1548665879999,
    "trades": 0
  },
  {
    "openTime": 1548665880000,
    "open": "0.00035240",
    "high": "0.00035240",
    "low": "0.00035240",
    "close": "0.00035240",
    "volume": "0.00035240",
    "closeTime": 1548665939999,
    "trades": 0
  },
  {
    "openTime": 1548665940000,
    "open": "0.00035240",
    "high": "0.00035240",
    "low": "0.00035240",
    "close": "0.00035240",
    "volume": "0.00035240",
    "closeTime": 1548665999999,
    "trades": 0
  },
  {
    "openTime": 1548666000000,
    "open": "0.00035240",
    "high": "0.00035240",
    "low": "0.00035240",
    "close": "0.00035240",
    "volume": "0.00035240",
    "closeTime": 1548666059999,
    "trades": 0
  },
  {
    "openTime": 1548666060000,
    "open": "0.00035240",
    "high": "0.00035240",
    "low": "0.00035240",
    "close": "0.00035240",
    "volume": "0.00035240",
    "closeTime": 1548666119999,
    "trades": 0
  },
  {
    "openTime": 1548666120000,
    "open": "0.00035120",
    "high": "0.00035120",
    "low": "0.00035100",
    "close": "0.00035100",
    "volume": "0.00035120",
    "closeTime": 1548666179999,
    "trades": 4
  },
  {
    "openTime": 1548666180000,
    "open": "0.00035100",
    "high": "0.00035100",
    "low": "0.00035100",
    "close": "0.00035100",
    "volume": "0.00035100",
    "closeTime": 1548666239999,
    "trades": 1
  },
  {
    "openTime": 1548666240000,
    "open": "0.00035100",
    "high": "0.00035100",
    "low": "0.00035100",
    "close": "0.00035100",
    "volume": "0.00035100",
    "closeTime": 1548666299999,
    "trades": 0
  },
  {
    "openTime": 1548666300000,
    "open": "0.00035100",
    "high": "0.00035100",
    "low": "0.00035100",
    "close": "0.00035100",
    "volume": "0.00035100",
    "closeTime": 1548666359999,
    "trades": 0
  },
  {
    "openTime": 1548666360000,
    "open": "0.00035100",
    "high": "0.00035100",
    "low": "0.00035100",
    "close": "0.00035100",
    "volume": "0.00035100",
    "closeTime": 1548666419999,
    "trades": 0
  },
  {
    "openTime": 1548666420000,
    "open": "0.00035100",
    "high": "0.00035100",
    "low": "0.00035100",
    "close": "0.00035100",
    "volume": "0.00035100",
    "closeTime": 1548666479999,
    "trades": 0
  },
  {
    "openTime": 1548666480000,
    "open": "0.00035100",
    "high": "0.00035100",
    "low": "0.00035100",
    "close": "0.00035100",
    "volume": "0.00035100",
    "closeTime": 1548666539999,
    "trades": 0
  },
  {
    "openTime": 1548666540000,
    "open": "0.00035100",
    "high": "0.00035100",
    "low": "0.00035100",
    "close": "0.00035100",
    "volume": "0.00035100",
    "closeTime": 1548666599999,
    "trades": 0
  },
  {
    "openTime": 1548666600000,
    "open": "0.00035100",
    "high": "0.00035100",
    "low": "0.00035100",
    "close": "0.00035100",
    "volume": "0.00035100",
    "closeTime": 1548666659999,
    "trades": 0
  },
  {
    "openTime": 1548666660000,
    "open": "0.00035100",
    "high": "0.00035100",
    "low": "0.00035100",
    "close": "0.00035100",
    "volume": "0.00035100",
    "closeTime": 1548666719999,
    "trades": 0
  },
  {
    "openTime": 1548666720000,
    "open": "0.00035100",
    "high": "0.00035100",
    "low": "0.00035100",
    "close": "0.00035100",
    "volume": "0.00035100",
    "closeTime": 1548666779999,
    "trades": 0
  },
  {
    "openTime": 1548666780000,
    "open": "0.00035100",
    "high": "0.00035100",
    "low": "0.00035100",
    "close": "0.00035100",
    "volume": "0.00035100",
    "closeTime": 1548666839999,
    "trades": 0
  },
  {
    "openTime": 1548666840000,
    "open": "0.00035130",
    "high": "0.00035130",
    "low": "0.00035110",
    "close": "0.00035110",
    "volume": "0.00035130",
    "closeTime": 1548666899999,
    "trades": 2
  },
  {
    "openTime": 1548666900000,
    "open": "0.00035110",
    "high": "0.00035110",
    "low": "0.00035110",
    "close": "0.00035110",
    "volume": "0.00035110",
    "closeTime": 1548666959999,
    "trades": 0
  },
  {
    "openTime": 1548666960000,
    "open": "0.00035110",
    "high": "0.00035110",
    "low": "0.00035110",
    "close": "0.00035110",
    "volume": "0.00035110",
    "closeTime": 1548667019999,
    "trades": 0
  },
  {
    "openTime": 1548667020000,
    "open": "0.00035190",
    "high": "0.00035250",
    "low": "0.00035110",
    "close": "0.00035250",
    "volume": "0.00035190",
    "closeTime": 1548667079999,
    "trades": 16
  },
  {
    "openTime": 1548667080000,
    "open": "0.00035130",
    "high": "0.00035130",
    "low": "0.00035120",
    "close": "0.00035130",
    "volume": "0.00035130",
    "closeTime": 1548667139999,
    "trades": 10
  },
  {
    "openTime": 1548667140000,
    "open": "0.00035130",
    "high": "0.00035130",
    "low": "0.00035130",
    "close": "0.00035130",
    "volume": "0.00035130",
    "closeTime": 1548667199999,
    "trades": 0
  },
  {
    "openTime": 1548667200000,
    "open": "0.00035130",
    "high": "0.00035130",
    "low": "0.00035130",
    "close": "0.00035130",
    "volume": "0.00035130",
    "closeTime": 1548667259999,
    "trades": 0
  },
  {
    "openTime": 1548667260000,
    "open": "0.00035130",
    "high": "0.00035130",
    "low": "0.00035130",
    "close": "0.00035130",
    "volume": "0.00035130",
    "closeTime": 1548667319999,
    "trades": 0
  },
  {
    "openTime": 1548667320000,
    "open": "0.00035130",
    "high": "0.00035130",
    "low": "0.00035130",
    "close": "0.00035130",
    "volume": "0.00035130",
    "closeTime": 1548667379999,
    "trades": 0
  },
  {
    "openTime": 1548667380000,
    "open": "0.00035130",
    "high": "0.00035130",
    "low": "0.00035130",
    "close": "0.00035130",
    "volume": "0.00035130",
    "closeTime": 1548667439999,
    "trades": 0
  },
  {
    "openTime": 1548667440000,
    "open": "0.00035130",
    "high": "0.00035130",
    "low": "0.00035130",
    "close": "0.00035130",
    "volume": "0.00035130",
    "closeTime": 1548667499999,
    "trades": 0
  },
  {
    "openTime": 1548667500000,
    "open": "0.00035130",
    "high": "0.00035130",
    "low": "0.00035130",
    "close": "0.00035130",
    "volume": "0.00035130",
    "closeTime": 1548667559999,
    "trades": 0
  },
  {
    "openTime": 1548667560000,
    "open": "0.00035130",
    "high": "0.00035130",
    "low": "0.00035130",
    "close": "0.00035130",
    "volume": "0.00035130",
    "closeTime": 1548667619999,
    "trades": 0
  },
  {
    "openTime": 1548667620000,
    "open": "0.00035130",
    "high": "0.00035130",
    "low": "0.00035130",
    "close": "0.00035130",
    "volume": "0.00035130",
    "closeTime": 1548667679999,
    "trades": 0
  },
  {
    "openTime": 1548667680000,
    "open": "0.00035130",
    "high": "0.00035130",
    "low": "0.00035130",
    "close": "0.00035130",
    "volume": "0.00035130",
    "closeTime": 1548667739999,
    "trades": 0
  },
  {
    "openTime": 1548667740000,
    "open": "0.00035130",
    "high": "0.00035130",
    "low": "0.00035130",
    "close": "0.00035130",
    "volume": "0.00035130",
    "closeTime": 1548667799999,
    "trades": 0
  },
  {
    "openTime": 1548667800000,
    "open": "0.00035130",
    "high": "0.00035130",
    "low": "0.00035130",
    "close": "0.00035130",
    "volume": "0.00035130",
    "closeTime": 1548667859999,
    "trades": 0
  },
  {
    "openTime": 1548667860000,
    "open": "0.00035130",
    "high": "0.00035130",
    "low": "0.00035130",
    "close": "0.00035130",
    "volume": "0.00035130",
    "closeTime": 1548667919999,
    "trades": 0
  },
  {
    "openTime": 1548667920000,
    "open": "0.00035130",
    "high": "0.00035130",
    "low": "0.00035130",
    "close": "0.00035130",
    "volume": "0.00035130",
    "closeTime": 1548667979999,
    "trades": 0
  },
  {
    "openTime": 1548667980000,
    "open": "0.00035130",
    "high": "0.00035130",
    "low": "0.00035130",
    "close": "0.00035130",
    "volume": "0.00035130",
    "closeTime": 1548668039999,
    "trades": 0
  },
  {
    "openTime": 1548668040000,
    "open": "0.00035130",
    "high": "0.00035130",
    "low": "0.00035130",
    "close": "0.00035130",
    "volume": "0.00035130",
    "closeTime": 1548668099999,
    "trades": 0
  },
  {
    "openTime": 1548668100000,
    "open": "0.00035130",
    "high": "0.00035130",
    "low": "0.00035130",
    "close": "0.00035130",
    "volume": "0.00035130",
    "closeTime": 1548668159999,
    "trades": 0
  },
  {
    "openTime": 1548668160000,
    "open": "0.00035130",
    "high": "0.00035130",
    "low": "0.00035130",
    "close": "0.00035130",
    "volume": "0.00035130",
    "closeTime": 1548668219999,
    "trades": 0
  },
  {
    "openTime": 1548668220000,
    "open": "0.00035160",
    "high": "0.00035160",
    "low": "0.00035140",
    "close": "0.00035150",
    "volume": "0.00035160",
    "closeTime": 1548668279999,
    "trades": 4
  },
  {
    "openTime": 1548668280000,
    "open": "0.00035150",
    "high": "0.00035150",
    "low": "0.00035150",
    "close": "0.00035150",
    "volume": "0.00035150",
    "closeTime": 1548668339999,
    "trades": 0
  },
  {
    "openTime": 1548668340000,
    "open": "0.00035240",
    "high": "0.00035250",
    "low": "0.00035150",
    "close": "0.00035150",
    "volume": "0.00035240",
    "closeTime": 1548668399999,
    "trades": 5
  },
  {
    "openTime": 1548668400000,
    "open": "0.00035150",
    "high": "0.00035150",
    "low": "0.00035150",
    "close": "0.00035150",
    "volume": "0.00035150",
    "closeTime": 1548668459999,
    "trades": 0
  },
  {
    "openTime": 1548668460000,
    "open": "0.00035330",
    "high": "0.00035420",
    "low": "0.00035330",
    "close": "0.00035350",
    "volume": "0.00035330",
    "closeTime": 1548668519999,
    "trades": 9
  },
  {
    "openTime": 1548668520000,
    "open": "0.00035350",
    "high": "0.00035350",
    "low": "0.00035350",
    "close": "0.00035350",
    "volume": "0.00035350",
    "closeTime": 1548668579999,
    "trades": 0
  },
  {
    "openTime": 1548668580000,
    "open": "0.00035350",
    "high": "0.00035350",
    "low": "0.00035350",
    "close": "0.00035350",
    "volume": "0.00035350",
    "closeTime": 1548668639999,
    "trades": 0
  },
  {
    "openTime": 1548668640000,
    "open": "0.00035360",
    "high": "0.00035360",
    "low": "0.00035360",
    "close": "0.00035360",
    "volume": "0.00035360",
    "closeTime": 1548668699999,
    "trades": 1
  },
  {
    "openTime": 1548668700000,
    "open": "0.00035360",
    "high": "0.00035360",
    "low": "0.00035360",
    "close": "0.00035360",
    "volume": "0.00035360",
    "closeTime": 1548668759999,
    "trades": 0
  },
  {
    "openTime": 1548668760000,
    "open": "0.00035350",
    "high": "0.00035360",
    "low": "0.00035350",
    "close": "0.00035360",
    "volume": "0.00035350",
    "closeTime": 1548668819999,
    "trades": 3
  },
  {
    "openTime": 1548668820000,
    "open": "0.00035370",
    "high": "0.00035370",
    "low": "0.00035350",
    "close": "0.00035350",
    "volume": "0.00035370",
    "closeTime": 1548668879999,
    "trades": 3
  },
  {
    "openTime": 1548668880000,
    "open": "0.00035330",
    "high": "0.00035380",
    "low": "0.00035330",
    "close": "0.00035380",
    "volume": "0.00035330",
    "closeTime": 1548668939999,
    "trades": 3
  },
  {
    "openTime": 1548668940000,
    "open": "0.00035220",
    "high": "0.00035310",
    "low": "0.00035200",
    "close": "0.00035310",
    "volume": "0.00035220",
    "closeTime": 1548668999999,
    "trades": 5
  },
  {
    "openTime": 1548669000000,
    "open": "0.00035310",
    "high": "0.00035310",
    "low": "0.00035310",
    "close": "0.00035310",
    "volume": "0.00035310",
    "closeTime": 1548669059999,
    "trades": 0
  },
  {
    "openTime": 1548669060000,
    "open": "0.00035360",
    "high": "0.00035380",
    "low": "0.00035360",
    "close": "0.00035380",
    "volume": "0.00035360",
    "closeTime": 1548669119999,
    "trades": 2
  },
  {
    "openTime": 1548669120000,
    "open": "0.00035370",
    "high": "0.00035380",
    "low": "0.00035370",
    "close": "0.00035380",
    "volume": "0.00035370",
    "closeTime": 1548669179999,
    "trades": 3
  },
  {
    "openTime": 1548669180000,
    "open": "0.00035380",
    "high": "0.00035380",
    "low": "0.00035380",
    "close": "0.00035380",
    "volume": "0.00035380",
    "closeTime": 1548669239999,
    "trades": 0
  },
  {
    "openTime": 1548669240000,
    "open": "0.00035380",
    "high": "0.00035380",
    "low": "0.00035380",
    "close": "0.00035380",
    "volume": "0.00035380",
    "closeTime": 1548669299999,
    "trades": 0
  },
  {
    "openTime": 1548669300000,
    "open": "0.00035250",
    "high": "0.00035250",
    "low": "0.00035200",
    "close": "0.00035200",
    "volume": "0.00035250",
    "closeTime": 1548669359999,
    "trades": 4
  },
  {
    "openTime": 1548669360000,
    "open": "0.00035170",
    "high": "0.00035170",
    "low": "0.00035170",
    "close": "0.00035170",
    "volume": "0.00035170",
    "closeTime": 1548669419999,
    "trades": 2
  },
  {
    "openTime": 1548669420000,
    "open": "0.00035160",
    "high": "0.00035160",
    "low": "0.00035110",
    "close": "0.00035110",
    "volume": "0.00035160",
    "closeTime": 1548669479999,
    "trades": 8
  },
  {
    "openTime": 1548669480000,
    "open": "0.00035110",
    "high": "0.00035110",
    "low": "0.00035110",
    "close": "0.00035110",
    "volume": "0.00035110",
    "closeTime": 1548669539999,
    "trades": 0
  },
  {
    "openTime": 1548669540000,
    "open": "0.00035110",
    "high": "0.00035110",
    "low": "0.00035110",
    "close": "0.00035110",
    "volume": "0.00035110",
    "closeTime": 1548669599999,
    "trades": 0
  },
  {
    "openTime": 1548669600000,
    "open": "0.00035110",
    "high": "0.00035110",
    "low": "0.00035110",
    "close": "0.00035110",
    "volume": "0.00035110",
    "closeTime": 1548669659999,
    "trades": 0
  },
  {
    "openTime": 1548669660000,
    "open": "0.00035120",
    "high": "0.00035120",
    "low": "0.00035120",
    "close": "0.00035120",
    "volume": "0.00035120",
    "closeTime": 1548669719999,
    "trades": 2
  },
  {
    "openTime": 1548669720000,
    "open": "0.00035280",
    "high": "0.00035280",
    "low": "0.00035280",
    "close": "0.00035280",
    "volume": "0.00035280",
    "closeTime": 1548669779999,
    "trades": 2
  },
  {
    "openTime": 1548669780000,
    "open": "0.00035280",
    "high": "0.00035280",
    "low": "0.00035280",
    "close": "0.00035280",
    "volume": "0.00035280",
    "closeTime": 1548669839999,
    "trades": 0
  },
  {
    "openTime": 1548669840000,
    "open": "0.00035280",
    "high": "0.00035280",
    "low": "0.00035280",
    "close": "0.00035280",
    "volume": "0.00035280",
    "closeTime": 1548669899999,
    "trades": 0
  },
  {
    "openTime": 1548669900000,
    "open": "0.00035280",
    "high": "0.00035280",
    "low": "0.00035280",
    "close": "0.00035280",
    "volume": "0.00035280",
    "closeTime": 1548669959999,
    "trades": 0
  },
  {
    "openTime": 1548669960000,
    "open": "0.00035280",
    "high": "0.00035280",
    "low": "0.00035280",
    "close": "0.00035280",
    "volume": "0.00035280",
    "closeTime": 1548670019999,
    "trades": 0
  },
  {
    "openTime": 1548670020000,
    "open": "0.00035280",
    "high": "0.00035280",
    "low": "0.00035280",
    "close": "0.00035280",
    "volume": "0.00035280",
    "closeTime": 1548670079999,
    "trades": 0
  },
  {
    "openTime": 1548670080000,
    "open": "0.00035280",
    "high": "0.00035280",
    "low": "0.00035280",
    "close": "0.00035280",
    "volume": "0.00035280",
    "closeTime": 1548670139999,
    "trades": 0
  },
  {
    "openTime": 1548670140000,
    "open": "0.00035280",
    "high": "0.00035280",
    "low": "0.00035280",
    "close": "0.00035280",
    "volume": "0.00035280",
    "closeTime": 1548670199999,
    "trades": 0
  },
  {
    "openTime": 1548670200000,
    "open": "0.00035280",
    "high": "0.00035280",
    "low": "0.00035280",
    "close": "0.00035280",
    "volume": "0.00035280",
    "closeTime": 1548670259999,
    "trades": 0
  },
  {
    "openTime": 1548670260000,
    "open": "0.00035280",
    "high": "0.00035280",
    "low": "0.00035280",
    "close": "0.00035280",
    "volume": "0.00035280",
    "closeTime": 1548670319999,
    "trades": 0
  },
  {
    "openTime": 1548670320000,
    "open": "0.00035280",
    "high": "0.00035280",
    "low": "0.00035280",
    "close": "0.00035280",
    "volume": "0.00035280",
    "closeTime": 1548670379999,
    "trades": 0
  },
  {
    "openTime": 1548670380000,
    "open": "0.00035280",
    "high": "0.00035280",
    "low": "0.00035280",
    "close": "0.00035280",
    "volume": "0.00035280",
    "closeTime": 1548670439999,
    "trades": 0
  },
  {
    "openTime": 1548670440000,
    "open": "0.00035280",
    "high": "0.00035280",
    "low": "0.00035280",
    "close": "0.00035280",
    "volume": "0.00035280",
    "closeTime": 1548670499999,
    "trades": 0
  },
  {
    "openTime": 1548670500000,
    "open": "0.00035280",
    "high": "0.00035280",
    "low": "0.00035280",
    "close": "0.00035280",
    "volume": "0.00035280",
    "closeTime": 1548670559999,
    "trades": 0
  },
  {
    "openTime": 1548670560000,
    "open": "0.00035280",
    "high": "0.00035280",
    "low": "0.00035280",
    "close": "0.00035280",
    "volume": "0.00035280",
    "closeTime": 1548670619999,
    "trades": 0
  },
  {
    "openTime": 1548670620000,
    "open": "0.00035280",
    "high": "0.00035280",
    "low": "0.00035280",
    "close": "0.00035280",
    "volume": "0.00035280",
    "closeTime": 1548670679999,
    "trades": 0
  },
  {
    "openTime": 1548670680000,
    "open": "0.00035280",
    "high": "0.00035280",
    "low": "0.00035280",
    "close": "0.00035280",
    "volume": "0.00035280",
    "closeTime": 1548670739999,
    "trades": 0
  },
  {
    "openTime": 1548670740000,
    "open": "0.00035280",
    "high": "0.00035280",
    "low": "0.00035280",
    "close": "0.00035280",
    "volume": "0.00035280",
    "closeTime": 1548670799999,
    "trades": 0
  },
  {
    "openTime": 1548670800000,
    "open": "0.00035280",
    "high": "0.00035280",
    "low": "0.00035280",
    "close": "0.00035280",
    "volume": "0.00035280",
    "closeTime": 1548670859999,
    "trades": 0
  },
  {
    "openTime": 1548670860000,
    "open": "0.00035280",
    "high": "0.00035280",
    "low": "0.00035280",
    "close": "0.00035280",
    "volume": "0.00035280",
    "closeTime": 1548670919999,
    "trades": 0
  },
  {
    "openTime": 1548670920000,
    "open": "0.00035280",
    "high": "0.00035280",
    "low": "0.00035280",
    "close": "0.00035280",
    "volume": "0.00035280",
    "closeTime": 1548670979999,
    "trades": 0
  }
]